[
    {
        "BÖLÜM I":null
    },
    {
        "BÖLÜM I":null
    },
    {
        "BÖLÜM I":"CANLI HAYVANLAR; HAYVANSAL ÜRÜNLER"
    },
    {
        "BÖLÜM I":null
    },
    {
        "BÖLÜM I":null
    },
    {
        "BÖLÜM I":"    Notlar"
    },
    {
        "BÖLÜM I":null
    },
    {
        "BÖLÜM I":null
    },
    {
        "BÖLÜM I":" 1.  Bu bölümde adı geçen belirli bir hayvan cins veya türüne yapılan atıf, metinde aksi belirtilmedikçe, bu     "
    },
    {
        "BÖLÜM I":"      cins veya türün yavrusuna  da yapılmış sayılır."
    },
    {
        "BÖLÜM I":null
    },
    {
        "BÖLÜM I":" 2.  Metinde aksi belirtilmedikçe, tarifede \" kurutulmuş \" ürünlere yapılan atıf, suyu alınmış, "
    },
    {
        "BÖLÜM I":"      buharlaştırılmış veya dondurulmak suretiyle kurutulmuş (liyofilize) ürünlere de yapılmış sayılır."
    },
    {
        "BÖLÜM I":null
    },
    {
        "BÖLÜM I":null
    },
    {
        "BÖLÜM I":"FASIL 1"
    },
    {
        "BÖLÜM I":null
    },
    {
        "BÖLÜM I":null
    },
    {
        "BÖLÜM I":"CANLI HAYVANLAR"
    },
    {
        "BÖLÜM I":null
    },
    {
        "BÖLÜM I":null
    },
    {
        "BÖLÜM I":"  Not"
    },
    {
        "BÖLÜM I":null
    },
    {
        "BÖLÜM I":null
    },
    {
        "BÖLÜM I":" 1. Bu fasıla aşağıda yazılı olanların dışında kalan bütün canlı hayvanlar dahildir:"
    },
    {
        "BÖLÜM I":null
    },
    {
        "BÖLÜM I":"     (a) 03.01, 03.06, 03.07 veya 03.08 pozisyonlarına giren balıklar ve kabuklu hayvanlar, yumuşakçalar ve suda"
    },
    {
        "BÖLÜM I":"           yaşayan diğer omurgasız hayvanlar;"
    },
    {
        "BÖLÜM I":null
    },
    {
        "BÖLÜM I":"     (b) 30.02 pozisyonuna giren mikroorganizma kültürleri ve diğer ürünler; ve"
    },
    {
        "BÖLÜM I":null
    },
    {
        "BÖLÜM I":"     (c) 95.08 pozisyonundaki hayvanlar."
    }
]