[
    {
        "FASIL 95":null,
        "Unnamed: 1":null
    },
    {
        "FASIL 95":null,
        "Unnamed: 1":null
    },
    {
        "FASIL 95":"OYUNCAKLAR, OYUN VE SPOR MALZEMELERİ;",
        "Unnamed: 1":null
    },
    {
        "FASIL 95":"BUNLARIN AKSAM, PARÇA VE AKSESUARI",
        "Unnamed: 1":null
    },
    {
        "FASIL 95":null,
        "Unnamed: 1":null
    },
    {
        "FASIL 95":null,
        "Unnamed: 1":null
    },
    {
        "FASIL 95":"         Notlar",
        "Unnamed: 1":null
    },
    {
        "FASIL 95":null,
        "Unnamed: 1":null
    },
    {
        "FASIL 95":null,
        "Unnamed: 1":null
    },
    {
        "FASIL 95":"     1. Aşağıda yazılı olanlar bu fasıla dahil değildir:",
        "Unnamed: 1":null
    },
    {
        "FASIL 95":null,
        "Unnamed: 1":null
    },
    {
        "FASIL 95":"         (a) Mumlar (34.06 pozisyonu);",
        "Unnamed: 1":null
    },
    {
        "FASIL 95":null,
        "Unnamed: 1":null
    },
    {
        "FASIL 95":"         (b) 36.04 pozisyonundaki havai fişekler veya diğer pirotekni eşyası;",
        "Unnamed: 1":null
    },
    {
        "FASIL 95":null,
        "Unnamed: 1":null
    },
    {
        "FASIL 95":"         (c) 39. fasıldaki, 42.06 pozisyonundaki veya XI. Bölüm'deki balık avı için uzunluğuna kesilmiş fakat",
        "Unnamed: 1":null
    },
    {
        "FASIL 95":"              olta haline getirilmemiş iplikler, monofilamentler, misinalar veya kaytanlar ve benzerleri;",
        "Unnamed: 1":null
    },
    {
        "FASIL 95":null,
        "Unnamed: 1":null
    },
    {
        "FASIL 95":"         (d) 42.02, 43.03 veya 43.04 pozisyonlarındaki spor çantaları veya diğer taşımaya mahsus eşya;",
        "Unnamed: 1":null
    },
    {
        "FASIL 95":null,
        "Unnamed: 1":null
    },
    {
        "FASIL 95":"         (e) Dokumaya elverişli maddelerden 61. veya 62. fasıldaki karnaval giyim eşyası;",
        "Unnamed: 1":null
    },
    {
        "FASIL 95":"              dokumaya elverişli maddelerden 61. veya 62. fasıldaki spor giyim ve özel giyim eşyası ",
        "Unnamed: 1":null
    },
    {
        "FASIL 95":"             (Dirsek, diz, kasık bölgesi yerlerinde pedler gibi koruyucu bilşenler içersin içermesin) ",
        "Unnamed: 1":null
    },
    {
        "FASIL 95":"            (örneğin eskrim veya futbol kaleci pantolonları)",
        "Unnamed: 1":null
    },
    {
        "FASIL 95":null,
        "Unnamed: 1":null
    },
    {
        "FASIL 95":"         (f) Dokumaya elverişli maddelerden bayraklar, flamalar, deniz veya kara taşıtları için ",
        "Unnamed: 1":null
    },
    {
        "FASIL 95":"             yelkenler (Fasıl 63);",
        "Unnamed: 1":null
    },
    {
        "FASIL 95":null,
        "Unnamed: 1":null
    },
    {
        "FASIL 95":"         (g) 64. fasıldaki spor ayakkabıları (buz pateni veya tekerlekli patenler hariç) veya 65. fasıldaki spor başlıkları;",
        "Unnamed: 1":null
    },
    {
        "FASIL 95":null,
        "Unnamed: 1":null
    },
    {
        "FASIL 95":"         (h) Bastonlar, kırbaçlar, binici kamçıları veya benzerleri (66.02 pozisyonu), bunların aksam ve parçaları",
        "Unnamed: 1":null
    },
    {
        "FASIL 95":"              (66.03 pozisyonu);",
        "Unnamed: 1":null
    },
    {
        "FASIL 95":null,
        "Unnamed: 1":null
    },
    {
        "FASIL 95":"         (ij) Yapma bebeklere ve diğer oyuncaklara mahsus takılmamış cam gözler (70.18 pozisyonu);",
        "Unnamed: 1":null
    },
    {
        "FASIL 95":null,
        "Unnamed: 1":null
    },
    {
        "FASIL 95":"         (k) XV. Bölüm'ün 2 no.lu Notu'nda tanımlandığı üzere adi metalden genel kullanıma mahsus aksam",
        "Unnamed: 1":null
    },
    {
        "FASIL 95":"              ve parçalar (Bölüm XV) veya plastikten benzeri eşya (Fasıl 39);",
        "Unnamed: 1":null
    },
    {
        "FASIL 95":null,
        "Unnamed: 1":null
    },
    {
        "FASIL 95":"         (l) Ziller, çanlar, gonglar ve benzerleri (83.06 pozisyonu);",
        "Unnamed: 1":null
    },
    {
        "FASIL 95":null,
        "Unnamed: 1":null
    },
    {
        "FASIL 95":"         (m) Sıvı pompaları (84.13 pozisyonu), sıvı veya gazların filtre edilmesine veya arıtılmasına mahsus",
        "Unnamed: 1":null
    },
    {
        "FASIL 95":"               cihaz ve aksamı (84.21 pozisyonu), elektrik motorları (85.01 pozisyonu), elektrik ",
        "Unnamed: 1":null
    },
    {
        "FASIL 95":"               transformatörleri (85.04 pozisyonu), Sesleri ve diğer fenomenleri kaydetmeye mahsus ",
        "Unnamed: 1":null
    },
    {
        "FASIL 95":"              diskler, bantlar, katı hal kalıcı depolama aygıtları, akıllı kartlar ve diğer masnetler ",
        "Unnamed: 1":null
    },
    {
        "FASIL 95":"             (kayıt yapılmış olsun olmasın) (85.23 pozisyonu), uzaktan kumanda etmeye mahsus ",
        "Unnamed: 1":null
    },
    {
        "FASIL 95":"             telsiz cihazları (85.26 pozisyonu) veya Infrared ile çalışan uzaktan kumanda cihazları (85.43 pozisyonu);",
        "Unnamed: 1":null
    },
    {
        "FASIL 95":null,
        "Unnamed: 1":null
    },
    {
        "FASIL 95":"         (n) XVII. Bölüm'deki spor kara taşıtları (kızaklar, yarış kızakları ve benzerleri hariç);",
        "Unnamed: 1":null
    },
    {
        "FASIL 95":null,
        "Unnamed: 1":null
    },
    {
        "FASIL 95":"         (o) Çocuk bisikletleri (87.12 pozisyonu);",
        "Unnamed: 1":null
    },
    {
        "FASIL 95":null,
        "Unnamed: 1":null
    },
    {
        "FASIL 95":"         (p) İnsansız hava taşıtları (88.06 pozisyonu)",
        "Unnamed: 1":null
    },
    {
        "FASIL 95":null,
        "Unnamed: 1":null
    },
    {
        "FASIL 95":"         (q) Spor için deniz taşıtları (kano ve kayıklar gibi) (Fasıl 89) ve bunları harekete getiren tertibat (ahşap",
        "Unnamed: 1":null
    },
    {
        "FASIL 95":"               oldukları takdirde, Fasıl 44);",
        "Unnamed: 1":null
    },
    {
        "FASIL 95":null,
        "Unnamed: 1":null
    },
    {
        "FASIL 95":"         (r) Spor veya açık hava oyunları için koruyucu gözlükler veya benzerleri (90.04 pozisyonu);",
        "Unnamed: 1":null
    },
    {
        "FASIL 95":null,
        "Unnamed: 1":null
    },
    {
        "FASIL 95":"         (s) Düdükler ve avcı düdükleri (92.08 pozisyonu);",
        "Unnamed: 1":null
    },
    {
        "FASIL 95":null,
        "Unnamed: 1":null
    },
    {
        "FASIL 95":"         (t) 93. fasıldaki silahlar ve diğer eşya;",
        "Unnamed: 1":null
    },
    {
        "FASIL 95":null,
        "Unnamed: 1":null
    },
    {
        "FASIL 95":"         (u) Her tür elektrikli çelenkler (94.05 pozisyonu)",
        "Unnamed: 1":null
    },
    {
        "FASIL 95":null,
        "Unnamed: 1":null
    },
    {
        "FASIL 95":"        (v) Monopod, bipod, tripod ve benzeri eşyalar (96.20 pozisyonu)",
        "Unnamed: 1":null
    },
    {
        "FASIL 95":null,
        "Unnamed: 1":null
    },
    {
        "FASIL 95":"         (y) Raket telleri, çadırlar ve diğer kamp eşyası veya eldivenler, tek parmak koruyucu eldivenler,",
        "Unnamed: 1":null
    },
    {
        "FASIL 95":"                tek parmak eldivenler ( mamul olduğu maddeye göresınıflandırılır); veya",
        "Unnamed: 1":null
    },
    {
        "FASIL 95":null,
        "Unnamed: 1":null
    },
    {
        "FASIL 95":"         (z) Sofra ve mutfak eşyası, tuvalet eşyası, halılar ve diğer dokumaya elverişli maddelerden zemin",
        "Unnamed: 1":null
    },
    {
        "FASIL 95":"                kaplamaları, giyim eşyası, yatak çarşafları, masa örtüleri, tuvalet ve mutfak bezleri ile benzeri fayda sağlayan",
        "Unnamed: 1":null
    },
    {
        "FASIL 95":"                eşyalar (mamul olduğu maddeye göre sınıflandırılır).",
        "Unnamed: 1":null
    },
    {
        "FASIL 95":null,
        "Unnamed: 1":null
    },
    {
        "FASIL 95":"     2. Bu fasıla, önemsiz sayılacak ölçüde tabii inciler veya kültür incileri, kıymetli veya yarı kıymetli ",
        "Unnamed: 1":null
    },
    {
        "FASIL 95":"         taşları (tabii, sentetik veya terkip yoluyla elde edilmiş), kıymetli metaller veya kıymetli metallerle ",
        "Unnamed: 1":null
    },
    {
        "FASIL 95":"        kaplama metalleri içeren eşya dahildir.",
        "Unnamed: 1":null
    },
    {
        "FASIL 95":null,
        "Unnamed: 1":null
    },
    {
        "FASIL 95":"     3. Yukarıda 1 no.lu not hükmü saklı kalmak şartıyla, sadece veya esas itibariyle bu fasıla giren eşya ",
        "Unnamed: 1":null
    },
    {
        "FASIL 95":"         ile kullanılmaya elverişli olan aksam, parça ve aksesuar, ait oldukları eşyanın pozisyonunda ",
        "Unnamed: 1":null
    },
    {
        "FASIL 95":"         sınıflandırılırlar.",
        "Unnamed: 1":null
    },
    {
        "FASIL 95":null,
        "Unnamed: 1":null
    },
    {
        "FASIL 95":"     4. Yukarıdaki Not 1 hükümleri saklı kalmak kaydıyla, 95.03 pozisyonu, diğerleri meyanında, Yorum  ",
        "Unnamed: 1":null
    },
    {
        "FASIL 95":"          Kurallarının 3 (b)'ye  göre set olarak kabul edilemeyen veya ayrı olarak sunulduklarında diğer ",
        "Unnamed: 1":null
    },
    {
        "FASIL 95":"         pozisyonlarda sınıflandırılacak olan bir veya daha fazla parça ile birleştirilmiş bu pozisyona",
        "Unnamed: 1":null
    },
    {
        "FASIL 95":"         dahil eşyayı, perakende satılacak hale getirilmiş olmaları ve bir araya getirilen ",
        "Unnamed: 1":null
    },
    {
        "FASIL 95":"         eşyaların oyuncağın mümeyyiz vasfını taşımaları şartıyla içerir.",
        "Unnamed: 1":null
    },
    {
        "FASIL 95":null,
        "Unnamed: 1":null
    },
    {
        "FASIL 95":"     5. 95.03 pozisyonu, biçimleri, şekilleri veya yapıldıkları maddeye dayanılarak,  münhasıran hayvanlar",
        "Unnamed: 1":null
    },
    {
        "FASIL 95":"         için tasarlanmış olduğu anlaşılabilen eşyayı, örneğin \" evcil hayvan oyuncakları \"nı (kendi uygun",
        "Unnamed: 1":null
    },
    {
        "FASIL 95":"         pozisyonlarında sınıflandırılır) kapsamaz.",
        "Unnamed: 1":null
    },
    {
        "FASIL 95":null,
        "Unnamed: 1":null
    },
    {
        "FASIL 95":"     6. 95.08 pozisyonu anlamında;",
        "Unnamed: 1":null
    },
    {
        "FASIL 95":"        (a) \"Eğlence parkı gezinti eşyası\" ifadesi, bir kişiyi veya kişileri su yolları da dahil olmak üzere sabit veya sınırlı",
        "Unnamed: 1":null
    },
    {
        "FASIL 95":"               bir parkur üzerinde veya esas olarak eğlence amaçları için tanımlanmış bir alan içinde taşıyan, ",
        "Unnamed: 1":null
    },
    {
        "FASIL 95":"              veya yönlendiren bir cihaz veya cihaz veya ekipman kombinasyonu anlamına gelir. Bu tür eşya bir eğlence",
        "Unnamed: 1":null
    },
    {
        "FASIL 95":"              parkı, tema parkı, su parkı veya panayır alanı ile birlikte olabilir. Bu eğlence parkı gezinti eşyası, konutlarda veya ",
        "Unnamed: 1":null
    },
    {
        "FASIL 95":"             oyun alanlarında yaygın olarak kurulan türden ekipmanı içermez; ",
        "Unnamed: 1":null
    },
    {
        "FASIL 95":null,
        "Unnamed: 1":null
    },
    {
        "FASIL 95":"        (b) 'Su parkı eğlence eşyası' ifadesi, herhangi bir amaçla inşa edilmiş yolu olmayan, su içeren belirli bir alan ile",
        "Unnamed: 1":null
    },
    {
        "FASIL 95":"              karakterize edilen bir cihaz veya cihaz veya ekipman kombinasyonu anlamına gelir. Su parkı eğlenceleri yalnızca ",
        "Unnamed: 1":null
    },
    {
        "FASIL 95":"              su parkları için özel olarak tasarlanmış ekipmanları içerir; ve",
        "Unnamed: 1":null
    },
    {
        "FASIL 95":null,
        "Unnamed: 1":null
    },
    {
        "FASIL 95":"       (c) \"Fuar alanı eğlence eşyası\" ifadesi, genellikle bir operatör veya görevli kullanan ve kalıcı binalara veya bağımsız",
        "Unnamed: 1":null
    },
    {
        "FASIL 95":"              imtiyaz tezgahlarına kurulabilen şans, güç veya beceri oyunları anlamına gelir. Fuar alanı eğlenceleri",
        "Unnamed: 1":null
    },
    {
        "FASIL 95":"              95.04 pozisyonundaki teçhizatı kapsamaz. ",
        "Unnamed: 1":null
    },
    {
        "FASIL 95":null,
        "Unnamed: 1":null
    },
    {
        "FASIL 95":"         Bu pozisyon, tarifenin başka yerlerinde daha özel olarak sınıflandırılmış teçhizatı kapsamaz. ",
        "Unnamed: 1":null
    },
    {
        "FASIL 95":null,
        "Unnamed: 1":null
    },
    {
        "FASIL 95":"         Alt Pozisyon Notu",
        "Unnamed: 1":null
    },
    {
        "FASIL 95":null,
        "Unnamed: 1":null
    },
    {
        "FASIL 95":"        1. 9504.50 alt pozisyonu aşağıdaki eşyayı kapsar:",
        "Unnamed: 1":null
    },
    {
        "FASIL 95":null,
        "Unnamed: 1":null
    },
    {
        "FASIL 95":"            (a) Görüntülerin bir televizyon alıcı cihazında, monitörde veya diğer harici bir ekran veya yüzeyde ",
        "Unnamed: 1":null
    },
    {
        "FASIL 95":"                 görüntülendiği video oyun konsolları veya",
        "Unnamed: 1":null
    },
    {
        "FASIL 95":null,
        "Unnamed: 1":null
    },
    {
        "FASIL 95":"            (b) Portatif olsun olmasın dahili bir görüntü ekranına sahip video oyun makinaları",
        "Unnamed: 1":null
    },
    {
        "FASIL 95":null,
        "Unnamed: 1":null
    },
    {
        "FASIL 95":"            Bu alt pozisyon madeni para, banknot, banka kartları, jeton veya diğer herhangi bir ödeme aracı ile çalıştırılan  ",
        "Unnamed: 1":null
    },
    {
        "FASIL 95":"            video oyun konsollarını veya makinalarını kapsamaz. (9504.30 alt pozisyonu) ",
        "Unnamed: 1":null
    },
    {
        "FASIL 95":null,
        "Unnamed: 1":null
    },
    {
        "FASIL 95":null,
        "Unnamed: 1":null
    },
    {
        "FASIL 95":"        Ek  Not",
        "Unnamed: 1":null
    },
    {
        "FASIL 95":null,
        "Unnamed: 1":null
    },
    {
        "FASIL 95":"          1. 9505.10 alt pozisyonu:",
        "Unnamed: 1":null
    },
    {
        "FASIL 95":null,
        "Unnamed: 1":null
    },
    {
        "FASIL 95":"              (a) Geleneksel olarak noel eğlencelerinde kullanılan ve noel eğlenceleri için dizayn edilmiş ve üretilmiş",
        "Unnamed: 1":null
    },
    {
        "FASIL 95":null,
        "Unnamed: 1":"ürünler olarak tanınan eşyaları kapsar."
    },
    {
        "FASIL 95":null,
        "Unnamed: 1":null
    },
    {
        "FASIL 95":null,
        "Unnamed: 1":"Bunlar:"
    },
    {
        "FASIL 95":null,
        "Unnamed: 1":null
    },
    {
        "FASIL 95":null,
        "Unnamed: 1":"(1) İsanın doğuşuyla ilgili ürünler (örneğin geleneksel noel beşikleri, figürler, hayvanlar, noel yıldızları"
    },
    {
        "FASIL 95":null,
        "Unnamed: 1":"     (Bethlehem), üç kral ve doğum sahneleri vb.)"
    },
    {
        "FASIL 95":null,
        "Unnamed: 1":null
    },
    {
        "FASIL 95":null,
        "Unnamed: 1":"(2) Uzun zamandan beri var olan ulusal gelenekler nedeniyle noel eğlencesi ürünü olarak kabul edilmiş eşya:"
    },
    {
        "FASIL 95":null,
        "Unnamed: 1":null
    },
    {
        "FASIL 95":null,
        "Unnamed: 1":"Örneğin:"
    },
    {
        "FASIL 95":null,
        "Unnamed: 1":null
    },
    {
        "FASIL 95":null,
        "Unnamed: 1":" - Suni noel ağaçları"
    },
    {
        "FASIL 95":null,
        "Unnamed: 1":" - Noel çorapları"
    },
    {
        "FASIL 95":null,
        "Unnamed: 1":" - İmitasyon noel pastası"
    },
    {
        "FASIL 95":null,
        "Unnamed: 1":" - Noel baba (kızaklı olsun olmasın) "
    },
    {
        "FASIL 95":null,
        "Unnamed: 1":" - Noel melekleri"
    },
    {
        "FASIL 95":null,
        "Unnamed: 1":null
    },
    {
        "FASIL 95":null,
        "Unnamed: 1":"Bu alt pozisyon noel eğlencelerinde özel olarak kullanılmayan fakat kış mevsiminde esas olarak  "
    },
    {
        "FASIL 95":null,
        "Unnamed: 1":"dekorasyon amacıyla kullanılan ( buz saçakları, kar kristalleri, yıldızlar, ren geyikleri, robinler, kar adamlar vb)"
    },
    {
        "FASIL 95":null,
        "Unnamed: 1":"(renkleri veya kıyafet\/donanımı noeli çağrıştırsın veya çağrıştırmasın) eşyayı kapsamaz."
    },
    {
        "FASIL 95":null,
        "Unnamed: 1":null
    },
    {
        "FASIL 95":"             (b) Noel ağaçları için dekorasyon eşyası",
        "Unnamed: 1":null
    },
    {
        "FASIL 95":null,
        "Unnamed: 1":null
    },
    {
        "FASIL 95":null,
        "Unnamed: 1":"Bunlar noel ağaçlarına asılmak üzere tasarlanmıştır (Örneğin dayanıksız ve hafif malzemeden)"
    }
]